pybot/__init__.py
pybot/launcher.py
dc_pybot-0.1.2.dist-info/METADATA
dc_pybot-0.1.2.dist-info/WHEEL
dc_pybot-0.1.2.dist-info/entry_points.txt
dc_pybot-0.1.2.dist-info/top_level.txt
dc_pybot-0.1.2.dist-info/RECORD
