Metadata-Version: 2.4
Name: dc-pybot
Version: 0.1.2
Summary: A Discord bot written in Python.
Author: DEAMJAVA
Author-email: deamminecraft3@gmail.com
Requires-Python: >=3.12
Requires-Dist: requests
Dynamic: author
Dynamic: author-email
Dynamic: description
Dynamic: description-content-type
Dynamic: requires-dist
Dynamic: requires-python
Dynamic: summary
